bet_optimizer.py
tests/__init__.py
tests/test_bet_optimizer.py
bet_optimizer-0.0.2.dist-info/LICENSE
bet_optimizer-0.0.2.dist-info/METADATA
bet_optimizer-0.0.2.dist-info/WHEEL
bet_optimizer-0.0.2.dist-info/top_level.txt
bet_optimizer-0.0.2.dist-info/RECORD
